lzhlib.cpython-39-x86_64-linux-gnu.so
lhafile-0.3.1.dist-info/COPYING.txt
lhafile-0.3.1.dist-info/WHEEL
lhafile-0.3.1.dist-info/METADATA
lhafile-0.3.1.dist-info/top_level.txt
lhafile-0.3.1.dist-info/RECORD
lhafile/__init__.py
lhafile/lhafile.py
